topsis/__init__.py
topsis/topsis.py
topsis_anoushka_102303312-1.0.1.dist-info/licenses/LICENSE
topsis_anoushka_102303312-1.0.1.dist-info/METADATA
topsis_anoushka_102303312-1.0.1.dist-info/WHEEL
topsis_anoushka_102303312-1.0.1.dist-info/entry_points.txt
topsis_anoushka_102303312-1.0.1.dist-info/top_level.txt
topsis_anoushka_102303312-1.0.1.dist-info/RECORD
