Metadata-Version: 2.4
Name: Topsis-Anoushka-102303312
Version: 1.0.1
Summary: TOPSIS Implementation in Python
Author: Anoushka Singh
Author-email: anoushka@example.com
License-File: LICENSE
Requires-Dist: pandas
Requires-Dist: numpy
Dynamic: author
Dynamic: author-email
Dynamic: description
Dynamic: description-content-type
Dynamic: license-file
Dynamic: requires-dist
Dynamic: summary
